{"per_page":25,"total":3,"current":1,"data":[{"title":"[Swift]SF Symbols 정리","date":"2020-08-07T13:56:59.000Z","date_formatted":{"ll":"Aug 7, 2020","L":"08/07/2020","MM-DD":"08-07"},"excerpt":"","link":"2020/08/07/Swift-SF-Sybols-정리","tags":["SFSymbols"],"categories":["ios"]},{"title":"[Swift]SF Symbols 정리","date":"2020-08-07T13:56:59.000Z","date_formatted":{"ll":"Aug 7, 2020","L":"08/07/2020","MM-DD":"08-07"},"excerpt":"","link":"2020/08/07/Swift-SF-Sybols-정리","tags":["SFSymbols"],"categories":["ios"]},{"title":"SDK와 API차이","date":"2020-08-05T08:47:00.000Z","date_formatted":{"ll":"Aug 5, 2020","L":"08/05/2020","MM-DD":"08-05"},"excerpt":"","link":"2020/08/05/POST/SDK와-API차이","tags":["공부"],"categories":["post"]},{"title":"[Swfit]FireBase이용하여 Google로그인 만들기","date":"2020-08-04T04:09:11.000Z","date_formatted":{"ll":"Aug 4, 2020","L":"08/04/2020","MM-DD":"08-04"},"excerpt":"","link":"2020/08/04/Swfit-FireBase이용하여-Google로그인-만들기","tags":["FireBase","GoogleLogin"],"categories":["ios"]},{"title":"[라이브러리]paper-onboarding","date":"2020-07-30T20:11:37.000Z","date_formatted":{"ll":"Jul 30, 2020","L":"07/30/2020","MM-DD":"07-30"},"thumbnail":"image/on.png","excerpt":"","link":"2020/07/30/라이브러리-paper-onboarding","tags":["paper-onboarding"],"categories":["Library"]},{"title":"[Swift]customUIView 만들기","date":"2020-07-25T15:18:31.000Z","date_formatted":{"ll":"Jul 25, 2020","L":"07/25/2020","MM-DD":"07-25"},"thumbnail":"/image/xib11.png","excerpt":"","link":"2020/07/25/Swift-customUIView-만들기","tags":["CustomUI","UIView"],"categories":["ios"]},{"title":"[Swift]PageView(with:ScrollView)","date":"2020-07-20T17:24:35.000Z","date_formatted":{"ll":"Jul 20, 2020","L":"07/20/2020","MM-DD":"07-20"},"excerpt":"","link":"2020/07/20/Swift-PageView-with-ScrollView","tags":["UIPageView","UIScrollView"],"categories":["ios"]},{"title":"[swift]UIScrollView 만들기","date":"2020-07-20T16:12:35.000Z","date_formatted":{"ll":"Jul 20, 2020","L":"07/20/2020","MM-DD":"07-20"},"thumbnail":"image/scroll.png","excerpt":"","link":"2020/07/20/swift-UIScrollView-만들기","tags":["Swift","UIScrollView"],"categories":["ios"]},{"title":"[Swift]NavigationBar 생략","date":"2020-07-20T14:49:00.000Z","date_formatted":{"ll":"Jul 20, 2020","L":"07/20/2020","MM-DD":"07-20"},"thumbnail":"/image/naviless.png","excerpt":"","link":"2020/07/20/Swift-네이베이션-바-생략","tags":["NavigationBar","Swift"],"categories":["ios"]},{"title":"[라이브러리]Kingfisher로 gif이미지 삽입","date":"2020-07-19T19:43:30.000Z","date_formatted":{"ll":"Jul 19, 2020","L":"07/19/2020","MM-DD":"07-19"},"thumbnail":"image/king.png","excerpt":"","link":"2020/07/19/Swift-Kingfisher","tags":["Kingfisher","gif"],"categories":["Library"]},{"title":"[기타]gifs","date":"2020-07-18T23:57:16.000Z","date_formatted":{"ll":"Jul 18, 2020","L":"07/18/2020","MM-DD":"07-18"},"excerpt":"","link":"2020/07/18/기타-gifs","tags":["gif"],"categories":["ios"]},{"title":"[Swift]navigationBar title 변경(다양한 문제들)","date":"2020-07-15T11:57:02.000Z","date_formatted":{"ll":"Jul 15, 2020","L":"07/15/2020","MM-DD":"07-15"},"excerpt":"","link":"2020/07/15/Swift-navigationBar-title-변경-다양한-문제들"},{"title":"[Swift]상업용 UIFont변경","date":"2020-07-15T11:53:26.000Z","date_formatted":{"ll":"Jul 15, 2020","L":"07/15/2020","MM-DD":"07-15"},"thumbnail":"/image/font6.png","excerpt":"","link":"2020/07/15/Swift-상업용-Font변경","tags":["UIFont"],"categories":["ios"]},{"title":"[Swift]UISearchController ?? searchController : searchBar","date":"2020-07-12T02:46:00.000Z","date_formatted":{"ll":"Jul 12, 2020","L":"07/12/2020","MM-DD":"07-12"},"thumbnail":"/image/seach.png","excerpt":"","link":"2020/07/12/Swift-UISearchController","tags":["SeachBar","Swift"],"categories":["ios"]},{"title":"[Swift]Json파일 가져오기(with: decoder)","date":"2020-07-12T02:45:28.000Z","date_formatted":{"ll":"Jul 12, 2020","L":"07/12/2020","MM-DD":"07-12"},"thumbnail":"image/json.png","excerpt":"","link":"2020/07/12/Swift-Json파일-가져오기-with-decoder","tags":["Bundle","JSON","Path","Swift"],"categories":["ios"]},{"title":"[Swift]UIView에 shadow주기","date":"2020-07-09T19:08:39.000Z","date_formatted":{"ll":"Jul 9, 2020","L":"07/09/2020","MM-DD":"07-09"},"thumbnail":"/image/shadow4.png","excerpt":"","link":"2020/07/09/Swift-UIView에-shadow주기","tags":["Shadow","Swift","UIView"],"categories":["ios"]},{"title":"[라이브러리]SnapKit으로 오토레이아웃 잡기","date":"2020-07-09T17:48:46.000Z","date_formatted":{"ll":"Jul 9, 2020","L":"07/09/2020","MM-DD":"07-09"},"thumbnail":"image/snapkit2.png","excerpt":"","link":"2020/07/09/라이브러리-SnapKit으로-오토레이아웃-잡기","tags":["SnapKit","Swift","라이브러리"],"categories":["Library"]},{"title":"[Swift]Text 줄바꿈(n,t,r)","date":"2020-07-08T11:44:50.000Z","date_formatted":{"ll":"Jul 8, 2020","L":"07/08/2020","MM-DD":"07-08"},"thumbnail":"/image/ntr.png","excerpt":"","link":"2020/07/08/Swift-Text-줄바꿈-n-t-r","tags":["Swift","Text","제어문자"],"categories":["ios"]},{"title":"[Swift]Launch screen 애니메이션 바(CAGradientLayer)","date":"2020-07-08T10:12:03.000Z","date_formatted":{"ll":"Jul 8, 2020","L":"07/08/2020","MM-DD":"07-08"},"thumbnail":"/image/grad.png","excerpt":"","link":"2020/07/08/Swift-Launch-screen-애니메이션-바","tags":["CAGradientLayer","Launch Screen","Swift","animation"],"categories":["ios"]},{"title":"[Swift]Cell에 shadow주기","date":"2020-07-08T09:56:53.000Z","date_formatted":{"ll":"Jul 8, 2020","L":"07/08/2020","MM-DD":"07-08"},"thumbnail":"/image/shadow.png","excerpt":"","link":"2020/07/08/Swift-Cell에-shadow주기","tags":["Shadow","Swift","layr"],"categories":["ios"]},{"title":"[Swift]CollectionViewCell에 애니메이션 주기(CAAnimation)","date":"2020-07-08T09:07:48.000Z","date_formatted":{"ll":"Jul 8, 2020","L":"07/08/2020","MM-DD":"07-08"},"thumbnail":"/image/acani.png","excerpt":"","link":"2020/07/08/Swift-CollectionViewCell에-애니메이션-주기","tags":["CAAnimation","Swift","UICollectionView"],"categories":["ios"]},{"title":"[Swift]Gesture 이해하기","date":"2020-06-25T15:17:16.000Z","date_formatted":{"ll":"Jun 25, 2020","L":"06/25/2020","MM-DD":"06-25"},"thumbnail":"/image/gestrue27.png","excerpt":"","link":"2020/06/25/Swift-Gesture-이해하기-2","tags":["Gesture","Swift"],"categories":["ios"]},{"title":"[Swift]Tuch 이해하기(touch로 이미지 끌어오기)","date":"2020-06-25T13:18:24.000Z","date_formatted":{"ll":"Jun 25, 2020","L":"06/25/2020","MM-DD":"06-25"},"thumbnail":"image/gesture20.png","excerpt":"","link":"2020/06/25/Swift-touch-이해하기","tags":["ImageView","Swift","Touch"],"categories":["ios"]},{"title":"[Swift]MapKit 이해하기-4(with: MKOverlayRenderer)","date":"2020-06-23T15:36:44.000Z","date_formatted":{"ll":"Jun 23, 2020","L":"06/23/2020","MM-DD":"06-23"},"excerpt":"","link":"2020/06/23/Swift-MapKit-이해하기-4","tags":["MapKit","Swift"],"categories":["ios"]},{"title":"[Swift]MapKit 이해하기-3","date":"2020-06-23T14:58:36.000Z","date_formatted":{"ll":"Jun 23, 2020","L":"06/23/2020","MM-DD":"06-23"},"excerpt":"","link":"2020/06/23/Swift-MapKit-이해하기-3","tags":["MapKit","Swift"],"categories":["ios"]}]}